README.md
setup.py
Guerilla.egg-info/PKG-INFO
Guerilla.egg-info/SOURCES.txt
Guerilla.egg-info/dependency_links.txt
Guerilla.egg-info/requires.txt
Guerilla.egg-info/top_level.txt
guerilla/__init__.py
guerilla/data_handler.py
guerilla/players.py
guerilla/data/hyper_params/neural_net/default.yaml
guerilla/data/weights/default.p
guerilla/play/__init__.py
guerilla/play/game.py
guerilla/play/neural_net.py
guerilla/play/search.py
guerilla/play/search_helpers.py
guerilla/play/uci.py
scripts/Guerilla