Metadata-Version: 1.0
Name: Guerilla
Version: 1.0.2
Summary: Deep Learning Chess Engine
Home-page: https://www.python.org/sigs/distutils-sig/
Author: Stephane Aroca-Ouellette
Author-email: stephanearocaouellette@gmail.com
License: MIT
Platform: UNKNOWN
